README.md
setup.cfg
setup.py
cli/__init__.py
cli/src/__init__.py
cli/src/ssm_cli.py
cli/src/ssm_client.py
cli/tests/__init__.py
cli/tests/int/__init__.py
cli/tests/int/test_ssm_cli.py
cli/tests/unit/__init__.py
cli/tests/unit/test_ssm_client.py
ssm_simple_cli.egg-info/PKG-INFO
ssm_simple_cli.egg-info/SOURCES.txt
ssm_simple_cli.egg-info/dependency_links.txt
ssm_simple_cli.egg-info/entry_points.txt
ssm_simple_cli.egg-info/requires.txt
ssm_simple_cli.egg-info/top_level.txt