Metadata-Version: 2.1
Name: ssm-simple-cli
Version: 0.1.2
Summary: A simplistic CLI that works with AWS Systems Manager Parameter Store
Home-page: https://github.com/eyalstoler/ssm-simple-cli
Author: Eyal Stoler
Author-email: eyalstoler@gmail.com
License: MIT
Download-URL: https://github.com/eyalstoler/ssm-simple-cli/archive/v0.1.2.tar.gz
Keywords: python,cli,aws-cli,ssm,ssm-cli
Platform: UNKNOWN
Classifier: Development Status :: 3 - Alpha
Classifier: Intended Audience :: Developers
Classifier: Topic :: Software Development :: Build Tools
Classifier: License :: OSI Approved :: MIT License
Classifier: Programming Language :: Python :: 3
Classifier: Programming Language :: Python :: 3.4
Classifier: Programming Language :: Python :: 3.5
Classifier: Programming Language :: Python :: 3.6
Classifier: Programming Language :: Python :: 3.7
